credoapp/__init__.py
credoapp/app.py
credoapp/core/__init__.py
credoapp/core/_hf_type.py
credoapp/core/chat_service.py
credoapp/core/config.py
credoapp/core/features/__init__.py
credoapp/core/features/base.py
credoapp/core/features/basic_google.py
credoapp/core/features/llm_search.py
credoapp/core/features/rawwebsearch_agent.py
credoapp/core/features/websearch_agent.py
credoapp/core/model_names.py
credoapp/core/model_service.py
credoapp/core/server.py
credoapp/runner.py
credoapp-0.1.25.dist-info/METADATA
credoapp-0.1.25.dist-info/WHEEL
credoapp-0.1.25.dist-info/entry_points.txt
credoapp-0.1.25.dist-info/RECORD
